apple_image_generator/.DS_Store
apple_image_generator/__init__.py
apple_image_generator/main.py
apple_image_generator-0.1.0.dist-info/entry_points.txt
apple_image_generator-0.1.0.dist-info/WHEEL
apple_image_generator-0.1.0.dist-info/METADATA
apple_image_generator-0.1.0.dist-info/RECORD
